codingkeks/Color.py
codingkeks/__init__.py
codingkeks/terminal.py
codingkeks-0.0.1.dist-info/LICENSE
codingkeks-0.0.1.dist-info/METADATA
codingkeks-0.0.1.dist-info/WHEEL
codingkeks-0.0.1.dist-info/top_level.txt
codingkeks-0.0.1.dist-info/RECORD
